ytt_mcp.py
ytt_mcp-0.0.7.dist-info/METADATA
ytt_mcp-0.0.7.dist-info/WHEEL
ytt_mcp-0.0.7.dist-info/entry_points.txt
ytt_mcp-0.0.7.dist-info/licenses/LICENSE
ytt_mcp-0.0.7.dist-info/RECORD
