Metadata-Version: 2.4
Name: ytt-mcp
Version: 0.0.7
Summary: MCP Server to extract transcript from a YouTube video
Project-URL: Repository, https://github.com/deepakjois/ytt-mcp
Project-URL: Issues, https://github.com/deepakjois/ytt-mcp/issues
Author: Deepak Jois
Maintainer-email: Deepak Jois <deepak.jois@gmail.com>
License: MIT
License-File: LICENSE
Keywords: mcp,transcript,youtube
Requires-Python: >=3.10
Requires-Dist: fastmcp>=2.8.1
Requires-Dist: youtube-transcript-api>=1.1.0
